LICENSE
MANIFEST.in
README.rst
setup.py
ct_useragents/__init__.py
ct_useragents/admin.py
ct_useragents/apps.py
ct_useragents/forms.py
ct_useragents/models.py
ct_useragents/tests.py
ct_useragents/utils.py
ct_useragents/views.py
ct_useragents/migrations/0001_initial.py
ct_useragents/migrations/0002_visit_user.py
ct_useragents/migrations/__init__.py
django_ct_useragents.egg-info/PKG-INFO
django_ct_useragents.egg-info/SOURCES.txt
django_ct_useragents.egg-info/dependency_links.txt
django_ct_useragents.egg-info/requires.txt
django_ct_useragents.egg-info/top_level.txt